README.rst
setup.py
nicnames/__init__.py
nicnames/nicnames.py
nicnames/tld_data.py
nicnames/utilities.py
nicnames.egg-info/PKG-INFO
nicnames.egg-info/SOURCES.txt
nicnames.egg-info/dependency_links.txt
nicnames.egg-info/requires.txt
nicnames.egg-info/top_level.txt
nicnames.egg-info/zip-safe