Metadata-Version: 1.1
Name: nicnames
Version: 0.1.2
Summary: A collection of functions for performing whois and DNS queries.
Home-page: https://github.com/stephan765/nicnames
Author: Stephan Solomonidis
Author-email: stephan@stephan.io
License: BSD (3-Clause) License
Download-URL: https://pypi.python.org/pypi/nicnames
Platform: UNKNOWN
Classifier: License :: OSI Approved :: BSD License
Classifier: Operating System :: OS Independent
Classifier: Programming Language :: Python
Classifier: Programming Language :: Python :: 2.7
